libtiepie/__init__.py
libtiepie/api.py
libtiepie/const.py
libtiepie/device.py
libtiepie/devicelist.py
libtiepie/devicelistitem.py
libtiepie/exceptions.py
libtiepie/generator.py
libtiepie/library.py
libtiepie/network.py
libtiepie/networkservers.py
libtiepie/object.py
libtiepie/objectlist.py
libtiepie/oscilloscope.py
libtiepie/oscilloscopechannel.py
libtiepie/oscilloscopechannels.py
libtiepie/oscilloscopechanneltrigger.py
libtiepie/oscilloscopechanneltriggerhystereses.py
libtiepie/oscilloscopechanneltriggerlevels.py
libtiepie/oscilloscopechanneltriggertimes.py
libtiepie/oscilloscopetrigger.py
libtiepie/server.py
libtiepie/triggerinput.py
libtiepie/triggerinputs.py
libtiepie/triggeroutput.py
libtiepie/triggeroutputs.py
libtiepie/types.py
libtiepie/utils.py
libtiepie/_platform/__init__.py
libtiepie/_platform/_linux/__init__.py
libtiepie/_platform/_windows/__init__.py
python_libtiepie-1.5.0.dist-info/METADATA
python_libtiepie-1.5.0.dist-info/WHEEL
python_libtiepie-1.5.0.dist-info/top_level.txt
python_libtiepie-1.5.0.dist-info/RECORD
